nextfempy/__init__.py
nextfempy/nextfempy.py
nextfempy-0.3.7.dist-info/licenses/LICENSE
nextfempy-0.3.7.dist-info/METADATA
nextfempy-0.3.7.dist-info/WHEEL
nextfempy-0.3.7.dist-info/top_level.txt
nextfempy-0.3.7.dist-info/RECORD
