Metadata-Version: 2.4
Name: nextfempy
Version: 0.3.7
Summary: NextFEM REST API wrapper in pure Python
Home-page: https://github.com/NextFEM/NextFEMpy
Author: NextFEM
Author-email: info@nextfem.it
License: MIT
Classifier: Programming Language :: Python :: 3
Classifier: Operating System :: OS Independent
License-File: LICENSE
Requires-Dist: requests
Dynamic: author
Dynamic: author-email
Dynamic: classifier
Dynamic: description
Dynamic: description-content-type
Dynamic: home-page
Dynamic: license
Dynamic: license-file
Dynamic: requires-dist
Dynamic: summary
